fileioutilities/__init__.py
fileioutilities/file_io.py
fileioutilities/filesystem.py
fileioutilities/get_arguments.py
fileioutilities/hdfs.py
fileioutilities/http.py
fileioutilities/minio.py
file_io_utilities-0.0.16.dist-info/METADATA
file_io_utilities-0.0.16.dist-info/WHEEL
file_io_utilities-0.0.16.dist-info/top_level.txt
file_io_utilities-0.0.16.dist-info/RECORD
