Metadata-Version: 2.1
Name: file-io-utilities
Version: 0.0.16
Summary: Utils for file IO operations in Alida.
Home-page: UNKNOWN
Author: Alida research team
Author-email: salvatore.cipolla@eng.it
License: UNKNOWN
Platform: UNKNOWN
Classifier: Programming Language :: Python :: 3
Classifier: License :: OSI Approved :: MIT License
Classifier: Operating System :: OS Independent
Requires-Python: >=3.6
Requires-Dist: hdfs (>=2.0.0)
Requires-Dist: boto3 (>=1.17.92)
Requires-Dist: requests (>=2.22.0)
Requires-Dist: alida-arg-parser (>=0.0.21)
